genevarevalidpkg/__init__.py
genevarevalidpkg/genvalidation.py
genevareutils-1.0.dist-info/LICENSE
genevareutils-1.0.dist-info/METADATA
genevareutils-1.0.dist-info/WHEEL
genevareutils-1.0.dist-info/top_level.txt
genevareutils-1.0.dist-info/RECORD
