Metadata-Version: 2.1
Name: genevareutils
Version: 1.0
Summary: Package for performing validation tasks for data of genevare
Home-page: UNKNOWN
Author: Pavan Kumar
Author-email: pawan.veeramraju@gmail.com
License: UNKNOWN
Platform: UNKNOWN
Classifier: Programming Language :: Python :: 3
Classifier: License :: OSI Approved :: MIT License
Classifier: Operating System :: OS Independent
Requires-Dist: pandas
Requires-Dist: numpy
Requires-Dist: openpyxl
Requires-Dist: argparse
Requires-Dist: xlsxwriter
